LICENCE.txt
README.txt
setup.py
call_polygon_api/__init__.py
call_polygon_api/api.py
call_polygon_api.egg-info/PKG-INFO
call_polygon_api.egg-info/SOURCES.txt
call_polygon_api.egg-info/dependency_links.txt
call_polygon_api.egg-info/top_level.txt