Metadata-Version: 2.1
Name: call-polygon-api
Version: 0.0.1
Summary: A package to call the polygon api
Author: <Jiayue Li & Max>
Author-email: <jl12143@nyu.edu>
License: MIT
Keywords: api
Classifier: Development Status :: 3 - Alpha
Classifier: Intended Audience :: Developers
Classifier: License :: OSI Approved :: MIT License
Classifier: Programming Language :: Python :: 3
License-File: LICENCE.txt
